acdecom.py
acdecom-2020.7.27.dist-info/LICENSE
acdecom-2020.7.27.dist-info/METADATA
acdecom-2020.7.27.dist-info/WHEEL
acdecom-2020.7.27.dist-info/top_level.txt
acdecom-2020.7.27.dist-info/RECORD
